dolg/dolg_model_pt.py
dolg/dolg_model_tf2.py
dolg/resnet_pt.py
dolg/resnet_tf2.py
dolg/tests/test_model.py
dolg/utils/__init__.py
dolg/utils/convert_pt_to_tf2.py
dolg/utils/download_weights.py
dolg/utils/extraction.py
dolg-0.1.5.1.dist-info/LICENSE
dolg-0.1.5.1.dist-info/METADATA
dolg-0.1.5.1.dist-info/WHEEL
dolg-0.1.5.1.dist-info/top_level.txt
dolg-0.1.5.1.dist-info/RECORD
