Metadata-Version: 2.1
Name: dolg
Version: 0.1.5.1
Summary: Re-implementation of DOLG paper in torch and tensorflow with converted checkpoints
Home-page: https://github.com/Shiro-LK/python-DOLG
Author: Shiro-LK
Author-email: shirosaki94@gmail.com
License: MIT License
Download-URL: https://github.com/Shiro-LK/python-DOLG.git
Keywords: DOLG for torch and tensorflow,pretrained weights,tensorflow,tf,pytorch,torch
Platform: UNKNOWN
Classifier: Development Status :: 5 - Production/Stable
Classifier: Programming Language :: Python :: 3.7
Classifier: Programming Language :: Python :: 3.8
Requires-Dist: numpy
Requires-Dist: pytest
